pype9/__init__.py
pype9/annotations.py
pype9/arguments.py
pype9/exceptions.py
pype9/plot.py
pype9/version.py
pype9/cmd/__init__.py
pype9/cmd/_utils.py
pype9/cmd/convert.py
pype9/cmd/help.py
pype9/cmd/plot.py
pype9/cmd/simulate.py
pype9/simulate/__init__.py
pype9/simulate/common/__init__.py
pype9/simulate/common/simulation.py
pype9/simulate/common/units.py
pype9/simulate/common/cells/__init__.py
pype9/simulate/common/cells/base.py
pype9/simulate/common/cells/with_synapses.py
pype9/simulate/common/cells/code_gen/__init__.py
pype9/simulate/common/cells/code_gen/paths/README
pype9/simulate/common/code_gen/__init__.py
pype9/simulate/common/code_gen/base.py
pype9/simulate/common/network/__init__.py
pype9/simulate/common/network/base.py
pype9/simulate/common/network/cell_wrapper.py
pype9/simulate/common/network/connectivity.py
pype9/simulate/common/network/synapses.py
pype9/simulate/common/network/values.py
pype9/simulate/nest/__init__.py
pype9/simulate/nest/simulation.py
pype9/simulate/nest/units.py
pype9/simulate/nest/cells/__init__.py
pype9/simulate/nest/cells/base.py
pype9/simulate/nest/cells/code_gen/__init__.py
pype9/simulate/nest/cells/code_gen/templates/Makefile-am.tmpl
pype9/simulate/nest/cells/code_gen/templates/bootstrap-sh.tmpl
pype9/simulate/nest/cells/code_gen/templates/configure-ac.tmpl
pype9/simulate/nest/cells/code_gen/templates/header.tmpl
pype9/simulate/nest/cells/code_gen/templates/main.tmpl
pype9/simulate/nest/cells/code_gen/templates/module-cpp.tmpl
pype9/simulate/nest/cells/code_gen/templates/module-header.tmpl
pype9/simulate/nest/cells/code_gen/templates/module_sli_init.tmpl
pype9/simulate/nest/cells/code_gen/templates/includes/macros.tmpl
pype9/simulate/nest/cells/code_gen/templates/includes/default/buffer_vars.tmpl
pype9/simulate/nest/cells/code_gen/templates/includes/default/destructor.tmpl
pype9/simulate/nest/cells/code_gen/templates/includes/default/dynamics_return.tmpl
pype9-0.2.dist-info/DESCRIPTION.rst
pype9-0.2.dist-info/METADATA
pype9-0.2.dist-info/RECORD
pype9-0.2.dist-info/WHEEL
pype9-0.2.dist-info/metadata.json
pype9-0.2.dist-info/top_level.txt
