Metadata-Version: 2.0
Name: pype9
Version: 0.2
Summary: PYthon PipelinEs for 9ML (Pype9) is a collection of Python pipelines for simulating networks of neuron models described in 9ML with various simulator backends.
Home-page: http://readthedocs.io/pype9
Author: The PyPe9 Team (see AUTHORS)
Author-email: tom.g.close@gmail.com
License: MIT
Keywords: NineML pipeline computational neuroscience modeling interoperability XML YAML JSON HDF5 9ML neuron nest
Platform: UNKNOWN
Classifier: Development Status :: 4 - Beta
Classifier: Environment :: Console
Classifier: Intended Audience :: Science/Research
Classifier: License :: OSI Approved :: MIT License
Classifier: Natural Language :: English
Classifier: Operating System :: OS Independent
Classifier: Programming Language :: Python :: 2
Classifier: Programming Language :: Python :: 2.7
Classifier: Programming Language :: Python :: 3
Classifier: Programming Language :: Python :: 3.4
Classifier: Programming Language :: Python :: 3.5
Classifier: Programming Language :: Python :: 3.6
Classifier: Topic :: Scientific/Engineering
Requires-Python: >=2.7, !=3.0.*, !=3.1.*, !=3.2.*, !=3.3.*, <4
Requires-Dist: nineml (>=1.0)
Requires-Dist: ninemlcatalog (>=0.1)
Requires-Dist: sympy (>=1.1)
Requires-Dist: Jinja2 (>=2.6)
Requires-Dist: docutils (>=0.10)
Requires-Dist: mock (>=1.0)
Requires-Dist: numpy (>=1.5)
Requires-Dist: quantities (>=0.11.1)
Requires-Dist: neo (>=0.5.1)
Requires-Dist: mpi4py (>=1.3.1)
Requires-Dist: pyNN (>=0.9.1)
Requires-Dist: lazyarray (>=0.2.7)
Requires-Dist: diophantine (>=0.2.0)
Requires-Dist: PyYAML (>=3.11)
Requires-Dist: h5py (>=2.7.0)
Requires-Dist: future (>=0.16)
Provides-Extra: plot
Requires-Dist: matplotlib (>=2.0); extra == 'plot'
